Metadata-Version: 1.1
Name: langdetect
Version: 1.0.4
Summary: Language detection library ported from Google's language-detection.
Home-page: https://github.com/Mimino666/langdetect
Author: Michal Mimino Danilak
Author-email: michal.danilak@gmail.com
License:    Copyright 2014-2015 Michal "Mimino" Danilak
